{
	"configurations" : 
	[
		{
			"directories" : 
			[
				{
					"build" : ".",
					"childIndexes" : 
					[
						1,
						2
					],
					"hasInstallRule" : true,
					"jsonFile" : "directory-.-Release-f5ebdc15457944623624.json",
					"minimumCMakeVersion" : 
					{
						"string" : "3.5"
					},
					"projectIndex" : 0,
					"source" : "."
				},
				{
					"build" : "src",
					"jsonFile" : "directory-src-Release-b6cf2213fc5053b67c22.json",
					"minimumCMakeVersion" : 
					{
						"string" : "3.5"
					},
					"parentIndex" : 0,
					"projectIndex" : 0,
					"source" : "src",
					"targetIndexes" : 
					[
						5,
						6
					]
				},
				{
					"build" : "test",
					"childIndexes" : 
					[
						3
					],
					"hasInstallRule" : true,
					"jsonFile" : "directory-test-Release-451c0598f41488bb20b9.json",
					"minimumCMakeVersion" : 
					{
						"string" : "3.5"
					},
					"parentIndex" : 0,
					"projectIndex" : 0,
					"source" : "test",
					"targetIndexes" : 
					[
						0
					]
				},
				{
					"build" : "test/googletest-main",
					"childIndexes" : 
					[
						4
					],
					"hasInstallRule" : true,
					"jsonFile" : "directory-test.googletest-main-Release-4e52cf26be5aab4b678f.json",
					"minimumCMakeVersion" : 
					{
						"string" : "3.5"
					},
					"parentIndex" : 2,
					"projectIndex" : 1,
					"source" : "test/googletest-main"
				},
				{
					"build" : "test/googletest-main/googlemock",
					"childIndexes" : 
					[
						5
					],
					"hasInstallRule" : true,
					"jsonFile" : "directory-test.googletest-main.googlemock-Release-0bd95ec3936f01e34aa1.json",
					"minimumCMakeVersion" : 
					{
						"string" : "3.5"
					},
					"parentIndex" : 3,
					"projectIndex" : 2,
					"source" : "test/googletest-main/googlemock",
					"targetIndexes" : 
					[
						1,
						2
					]
				},
				{
					"build" : "test/googletest-main/googletest",
					"hasInstallRule" : true,
					"jsonFile" : "directory-test.googletest-main.googletest-Release-0ab74b7fae486a609dce.json",
					"minimumCMakeVersion" : 
					{
						"string" : "3.5"
					},
					"parentIndex" : 4,
					"projectIndex" : 3,
					"source" : "test/googletest-main/googletest",
					"targetIndexes" : 
					[
						3,
						4
					]
				}
			],
			"name" : "Release",
			"projects" : 
			[
				{
					"childIndexes" : 
					[
						1
					],
					"directoryIndexes" : 
					[
						0,
						1,
						2
					],
					"name" : "compression_app",
					"targetIndexes" : 
					[
						0,
						5,
						6
					]
				},
				{
					"childIndexes" : 
					[
						2
					],
					"directoryIndexes" : 
					[
						3
					],
					"name" : "googletest-distribution",
					"parentIndex" : 0
				},
				{
					"childIndexes" : 
					[
						3
					],
					"directoryIndexes" : 
					[
						4
					],
					"name" : "gmock",
					"parentIndex" : 1,
					"targetIndexes" : 
					[
						1,
						2
					]
				},
				{
					"directoryIndexes" : 
					[
						5
					],
					"name" : "gtest",
					"parentIndex" : 2,
					"targetIndexes" : 
					[
						3,
						4
					]
				}
			],
			"targets" : 
			[
				{
					"directoryIndex" : 2,
					"id" : "CompressTests::@36f028580bb02cc8272a",
					"jsonFile" : "target-CompressTests-Release-d07c5be136ccc7a97f44.json",
					"name" : "CompressTests",
					"projectIndex" : 0
				},
				{
					"directoryIndex" : 4,
					"id" : "gmock::@dc4ca2e24c423f9b846e",
					"jsonFile" : "target-gmock-Release-e67144e1137560ba07a1.json",
					"name" : "gmock",
					"projectIndex" : 2
				},
				{
					"directoryIndex" : 4,
					"id" : "gmock_main::@dc4ca2e24c423f9b846e",
					"jsonFile" : "target-gmock_main-Release-f6b7f9db6958db68d87e.json",
					"name" : "gmock_main",
					"projectIndex" : 2
				},
				{
					"directoryIndex" : 5,
					"id" : "gtest::@cc21a7437b5421b761e4",
					"jsonFile" : "target-gtest-Release-0ac360e15f205c685e7c.json",
					"name" : "gtest",
					"projectIndex" : 3
				},
				{
					"directoryIndex" : 5,
					"id" : "gtest_main::@cc21a7437b5421b761e4",
					"jsonFile" : "target-gtest_main-Release-7d71e3d2e8ecc9c4fbe3.json",
					"name" : "gtest_main",
					"projectIndex" : 3
				},
				{
					"directoryIndex" : 1,
					"id" : "prolix::@145eef247bfb46b6828c",
					"jsonFile" : "target-prolix-Release-d515afee1cd9a6a0ed52.json",
					"name" : "prolix",
					"projectIndex" : 0
				},
				{
					"directoryIndex" : 1,
					"id" : "terse::@145eef247bfb46b6828c",
					"jsonFile" : "target-terse-Release-e9e4e1c9aa18a0852d79.json",
					"name" : "terse",
					"projectIndex" : 0
				}
			]
		}
	],
	"kind" : "codemodel",
	"paths" : 
	{
		"build" : "/Users/matiny0000/Documents/PhD/terse/build",
		"source" : "/Users/matiny0000/Documents/PhD/terse"
	},
	"version" : 
	{
		"major" : 2,
		"minor" : 5
	}
}
